{
  "generator-jhipster": {
    "applicationType": "monolith",
    "gitHubOrganization": "gbrlcnv",
    "baseName": "legalTech",
    "packageName": "it.etianus.legal",
    "serverPort": 8080,
    "serviceDiscoveryType": false,
    "authenticationType": "session",
    "uaaBaseName": "../uaa",
    "cacheProvider": "no",
    "enableHibernateCache": false,
    "websocket": false,
    "databaseType": "sql",
    "devDatabaseType": "h2Disk",
    "prodDatabaseType": "mysql",
    "searchEngine": false,
    "enableSwaggerCodegen": false,
    "messageBroker": false,
    "buildTool": "maven",
    "enableSocialSignIn": false,
    "useSass": false,
    "clientPackageManager": "yarn",
    "testFrameworks": [],
    "enableTranslation": true,
    "nativeLanguage": "it",
    "languages": [
      "en",
      "it"
    ],
    "clientFramework": "angularX",
    "jhipsterVersion": "4.14.1",
    "packageFolder": "it/etianus/legal",
    "rememberMeKey": "0d38382c359a170b8188dab7af4d5b53e6b786bd",
    "jhiPrefix": "jhi"
  }
}